{"LakeBodyOfWater": "http://schema.org/LakeBodyOfWater", "Movie": "http://schema.org/Movie", "Recipe": "http://schema.org/Recipe", "Dataset": "http://schema.org/Dataset", "EducationalOrganization": "http://schema.org/EducationalOrganization", "Hotel": "http://schema.org/Hotel", "JobPosting": "http://schema.org/JobPosting", "Event": "http://schema.org/Event", "LocalBusiness": "http://schema.org/LocalBusiness", "Product": "http://schema.org/Product", "AdministrativeArea": "http://schema.org/AdministrativeArea", "Airport": "http://schema.org/Airport", "Book": "http://schema.org/Book", "City": "http://schema.org/City", "CollegeOrUniversity": "http://schema.org/CollegeOrUniversity", "Continent": "http://schema.org/Continent", "Country": "http://schema.org/Country", "CreativeWork": "http://schema.org/CreativeWork", "GeoCoordinates": "http://schema.org/GeoCoordinates", "GovernmentOrganization": "http://schema.org/GovernmentOrganization", "Hospital": "http://schema.org/Hospital", "LandmarksOrHistoricalBuildings": "http://schema.org/LandmarksOrHistoricalBuildings", "Language": "http://schema.org/Language", "Library": "http://schema.org/Library", "Mountain": "http://schema.org/Mountain", "Museum": "http://schema.org/Museum", "MusicAlbum": "http://schema.org/MusicAlbum", "MusicRecording": "http://schema.org/MusicRecording", "Organization": "http://schema.org/Organization", "Painting": "http://schema.org/Painting", "Park": "http://schema.org/Park", "Person": "http://schema.org/Person", "Place": "http://schema.org/Place", "RadioStation": "http://schema.org/RadioStation", "Restaurant": "http://schema.org/Restaurant", "RiverBodyOfWater": "http://schema.org/RiverBodyOfWater", "School": "http://schema.org/School", "ShoppingCenter": "http://schema.org/ShoppingCenter", "SkiResort": "http://schema.org/SkiResort", "SportsEvent": "http://schema.org/SportsEvent", "SportsTeam": "http://schema.org/SportsTeam", "StadiumOrArena": "http://schema.org/StadiumOrArena", "TelevisionStation": "http://schema.org/TelevisionStation", "TVEpisode": "http://schema.org/TVEpisode"}